rankade/Consts.py
rankade/Rankade.py
rankade/RankadeExceptions.py
rankade/__init__.py
rankade/py.typed
rankade/api/Api.py
rankade/api/Endpoint.py
rankade/api/RankadeResponse.py
rankade/api/Token.py
rankade/api/__init__.py
rankade/models/Base.py
rankade/models/Error.py
rankade/models/Faction.py
rankade/models/Game.py
rankade/models/Match.py
rankade/models/NewMatch.py
rankade/models/NewMatchResponse.py
rankade/models/Player.py
rankade/models/Quota.py
rankade/models/Ranking.py
rankade/models/Subset.py
rankade/models/__init__.py
rankade.py-0.1.4.dist-info/LICENSE
rankade.py-0.1.4.dist-info/METADATA
rankade.py-0.1.4.dist-info/WHEEL
rankade.py-0.1.4.dist-info/top_level.txt
rankade.py-0.1.4.dist-info/RECORD
