Metadata-Version: 2.1
Name: rankade.py
Version: 0.1.4
Summary: Unofficial Python async wrapper for the Rankade API
Author-email: Calum Crawford <c@calumcrawford.com>
License: MIT License
Project-URL: Changelog, https://github.com/14zombies/Rankade.py/blob/master/CHANGELOG.md
Project-URL: Documentation, https://calumcrawford.com/rankadepy
Project-URL: Homepage, https://calumcrawford.com/rankadepy
Project-URL: Issues, https://github.com/14zombies/Rankade.py/issues
Project-URL: Repository, https://github.com/14zombies/Rankade.py.git
Classifier: Development Status :: 3 - Alpha
Classifier: License :: OSI Approved :: MIT License
Classifier: Programming Language :: Python :: 3
Classifier: Intended Audience :: Developers
Classifier: Operating System :: OS Independent
Classifier: Topic :: Software Development :: Libraries :: Python Modules
Requires-Python: >=3.12
License-File: LICENSE
Requires-Dist: aiohttp >=3.7
Requires-Dist: PyJWT >=2.4
Requires-Dist: enum-tools
Provides-Extra: all
Requires-Dist: rankade-py[dev,docs,tests] ; extra == 'all'
Provides-Extra: dev
Requires-Dist: coverage >=7.4 ; extra == 'dev'
Requires-Dist: build ; extra == 'dev'
Requires-Dist: packaging ; extra == 'dev'
Requires-Dist: twine ; extra == 'dev'
Requires-Dist: wheel ; extra == 'dev'
Provides-Extra: docs
Requires-Dist: sphinx ; extra == 'docs'
Requires-Dist: sphinxawesome-theme ; extra == 'docs'
Requires-Dist: myst-parser ; extra == 'docs'
Requires-Dist: enum-tools[sphinx] ; extra == 'docs'
Requires-Dist: sphinx-sitemap ; extra == 'docs'
Requires-Dist: sphinx-autodoc2 ; extra == 'docs'
Requires-Dist: linkify-it-py ; extra == 'docs'
Requires-Dist: sphinxcontrib.spelling ; extra == 'docs'
Provides-Extra: tests
Requires-Dist: rankade-py[dev] ; extra == 'tests'
Requires-Dist: enumtools ; extra == 'tests'
Requires-Dist: aioresponses ; extra == 'tests'
